{
  "characters": [
    {
      "id": 1,
      "name": "Han Solo",
      "occupation": "Smuggler",
      "weapon": "Blaster Pistol",
      "cartoon": true
    },
    {
      "id": 2,
      "name": "Luke Skywalker",
      "occupation": "Jedi Knight",
      "weapon": "Lightsaber",
      "cartoon": false
    },
    {
      "id": 3,
      "name": "Sponge Bob",
      "occupation": "Lives under the sea",
      "weapon": "Crabby Patty",
      "cartoon": true
    },
    {
      "name": "mousy",
      "occupation": "cheese thief",
      "weapon": "teeth",
      "id": 12
    },
    {
      "name": "HulkH (N)",
      "id": 4
    },
    {
      "id": 13,
      "name": "Marioso",
      "occupation": "Hunter",
      "weapon": "Gun",
      "cartoon": "on"
    },
    {
      "name": "String Fellow",
      "occupation": "Hero",
      "weapon": "Airwolf",
      "cartoon": "on",
      "id": 14
    }
  ]
}